beepm/Main.py
BeePM-0.1.dist-info/LICENSE.md
BeePM-0.1.dist-info/METADATA
BeePM-0.1.dist-info/WHEEL
BeePM-0.1.dist-info/top_level.txt
BeePM-0.1.dist-info/RECORD
