Metadata-Version: 2.1
Name: BeePM
Version: 0.1
Summary: An open-source package manager for GNU/Linux
Home-page: https://github.com/MolassesLover/Bee
Author: Maeve Garside
Author-email: 60114762+MolassesLover@users.noreply.github.com
License: GNU General Public License v3.0
Platform: UNKNOWN
License-File: LICENSE.md
